mcp_neocoder/__init__.py
mcp_neocoder/__main__.py
mcp_neocoder/action_templates.py
mcp_neocoder/add_lv_tools.py
mcp_neocoder/cypher_snippets.py
mcp_neocoder/decorators.py
mcp_neocoder/event_loop_manager.py
mcp_neocoder/extract_incarnation_types.py
mcp_neocoder/generators.py
mcp_neocoder/incarnation_registry.py
mcp_neocoder/init_db.py
mcp_neocoder/lv_ecosystem.py
mcp_neocoder/lv_integration.py
mcp_neocoder/lv_neo4j_storage.py
mcp_neocoder/lv_refined_output.py
mcp_neocoder/lv_templates.py
mcp_neocoder/polymorphic_adapter.py
mcp_neocoder/process_manager.py
mcp_neocoder/qdrant_manager.py
mcp_neocoder/qdrant_utils.py
mcp_neocoder/server.py
mcp_neocoder/tool_proposals.py
mcp_neocoder/tool_registry.py
mcp_neocoder/verify_incarnations.py
mcp_neocoder/verify_tools.py
mseep_mcp_neocoder-0.1.1.dist-info/licenses/LICENSE
mseep_mcp_neocoder-0.1.1.dist-info/METADATA
mseep_mcp_neocoder-0.1.1.dist-info/WHEEL
mseep_mcp_neocoder-0.1.1.dist-info/entry_points.txt
mseep_mcp_neocoder-0.1.1.dist-info/top_level.txt
mseep_mcp_neocoder-0.1.1.dist-info/RECORD
